LICENSE
README.md
setup.py
exouprf/__init__.py
exouprf/fit.py
exouprf/light_curve_models.py
exouprf/plotting.py
exouprf/utils.py
exouprf.egg-info/PKG-INFO
exouprf.egg-info/SOURCES.txt
exouprf.egg-info/dependency_links.txt
exouprf.egg-info/requires.txt
exouprf.egg-info/top_level.txt