Metadata-Version: 2.1
Name: exouprf
Version: 1.1.0
Summary: Tools for Light Curve Fitting
Home-page: https://github.com/radicamc/exoUPRF
Author: Michael Radica
Author-email: radicamc@uchicago.edu
License: MIT
Classifier: Development Status :: 3 - Alpha
Classifier: Intended Audience :: Science/Research
Classifier: License :: OSI Approved :: MIT License
Classifier: Operating System :: OS Independent
Classifier: Programming Language :: Python :: 3.10
License-File: LICENSE
Requires-Dist: batman-package
Requires-Dist: celerite
Requires-Dist: corner
Requires-Dist: dynesty
Requires-Dist: emcee
Requires-Dist: h5py
Requires-Dist: matplotlib
Requires-Dist: numpy
Requires-Dist: scipy
Provides-Extra: catwoman
Requires-Dist: exouprf; extra == "catwoman"
Requires-Dist: catwoman; extra == "catwoman"
